README.md
setup.cfg
setup.py
bin/podstar
podstar/__init__.py
podstar/enclosure.py
podstar/episode.py
podstar/errors.py
podstar/feed.py
podstar/feed_page.py
podstar/stream.py
podstar.egg-info/PKG-INFO
podstar.egg-info/SOURCES.txt
podstar.egg-info/dependency_links.txt
podstar.egg-info/requires.txt
podstar.egg-info/top_level.txt