Metadata-Version: 2.1
Name: podstar
Version: 1.0.0
Summary: An RSS-compatible podcast feed client.
Home-page: https://github.com/kenkeiter/podstar
Author: Kenneth Keiter
Author-email: ken@kenkeiter.com
License: MIT
Keywords: rss,podcast,feed
Platform: UNKNOWN
Requires-Python: >=3.3
